slapos.cookbook-1.0.451-py3.11-nspkg.pth
slapos/recipe/README.generic_cloudooo.rst
slapos/recipe/README.librecipe.rst
slapos/recipe/README.mkdirectory.rst
slapos/recipe/README.zero_knowledge.rst
slapos/recipe/_urlparse.py
slapos/recipe/_uuid.py
slapos/recipe/check_port_listening.py
slapos/recipe/copyfilelist.py
slapos/recipe/dcron.py
slapos/recipe/dropbear.py
slapos/recipe/equeue.py
slapos/recipe/free_port.py
slapos/recipe/gitinit.py
slapos/recipe/jsondump.py
slapos/recipe/logrotate.py
slapos/recipe/mkdirectory.py
slapos/recipe/neoppod.py
slapos/recipe/notifier.py
slapos/recipe/pbs.py
slapos/recipe/postgres.py
slapos/recipe/promise_plugin.py
slapos/recipe/publish.py
slapos/recipe/publish_early.py
slapos/recipe/publishurl.py
slapos/recipe/random.py
slapos/recipe/readline.py
slapos/recipe/request.py
slapos/recipe/shell.py
slapos/recipe/simplelogger.py
slapos/recipe/slapconfiguration.py
slapos/recipe/sshkeys_authority.py
slapos/recipe/switch_softwaretype.py
slapos/recipe/symbolic_link.py
slapos/recipe/trac.py
slapos/recipe/userinfo.py
slapos/recipe/wrapper.py
slapos/recipe/zero_knowledge.py
slapos/recipe/6tunnel/__init__.py
slapos/recipe/6tunnel/template/4to6.in
slapos/recipe/6tunnel/template/6to4.in
slapos/recipe/addresiliency/__init__.py
slapos/recipe/addresiliency/takeover.py
slapos/recipe/apacheperl/__init__.py
slapos/recipe/apacheperl/template/apache.in
slapos/recipe/apachephp/__init__.py
slapos/recipe/apachephp/template/apache.in
slapos/recipe/apachephp/template/php.ini.in
slapos/recipe/apacheproxy/__init__.py
slapos/recipe/apacheproxy/template/apache.in
slapos/recipe/certificate_authority/__init__.py
slapos/recipe/certificate_authority/certificate_authority.py
slapos/recipe/certificate_authority/template/openssl.cnf.ca.in
slapos/recipe/check_page_content/__init__.py
slapos/recipe/check_page_content/template/check_page_content.in
slapos/recipe/check_parameter/__init__.py
slapos/recipe/check_parameter/template/check_ipv4.py.in
slapos_cookbook-1.0.451.dist-info/METADATA
slapos_cookbook-1.0.451.dist-info/WHEEL
slapos_cookbook-1.0.451.dist-info/entry_points.txt
slapos_cookbook-1.0.451.dist-info/namespace_packages.txt
slapos_cookbook-1.0.451.dist-info/top_level.txt
slapos_cookbook-1.0.451.dist-info/zip-safe
slapos_cookbook-1.0.451.dist-info/RECORD
