Metadata-Version: 2.4
Name: slapos.cookbook
Version: 1.0.451
Summary: SlapOS recipes.
Home-page: https://lab.nexedi.com/nexedi/slapos
Maintainer: Nexedi
Maintainer-email: info@nexedi.com
License: GPLv3
Keywords: slapos recipe
Classifier: Framework :: Buildout :: Recipe
Classifier: Programming Language :: Python
Requires-Dist: jsonschema
Requires-Dist: netaddr
Requires-Dist: setuptools
Requires-Dist: inotify_simple
Requires-Dist: legacy-cgi; python_version >= "3.13"
Requires-Dist: lock_file
Requires-Dist: slapos.core
Requires-Dist: zc.buildout
Requires-Dist: zc.recipe.egg
Requires-Dist: pytz
Requires-Dist: passlib
Provides-Extra: test
Requires-Dist: bcrypt; extra == "test"
Requires-Dist: jsonschema; extra == "test"
Requires-Dist: mock; extra == "test"
Requires-Dist: psycopg2; extra == "test"
Requires-Dist: testfixtures; extra == "test"
Requires-Dist: requests; extra == "test"
Dynamic: classifier
Dynamic: description
Dynamic: home-page
Dynamic: keywords
Dynamic: license
Dynamic: maintainer
Dynamic: maintainer-email
Dynamic: provides-extra
Dynamic: requires-dist
Dynamic: summary
